tests/integration/__init__.py
tests/integration/common.py
tests/integration/test_credential.py
tests/integration/test_group.py
tests/integration/test_host.py
tests/integration/test_instance.py
tests/integration/test_inventory.py
tests/integration/test_job.py
tests/integration/test_organization.py
tests/integration/test_project.py
tests/integration/test_team.py
tests/integration/test_towerlib.py
tests/integration/test_user.py
towerlib/.VERSION
towerlib/AUTHORS.rst
towerlib/CONTRIBUTING.rst
towerlib/HISTORY.rst
towerlib/LICENSE
towerlib/Pipfile
towerlib/Pipfile.lock
towerlib/README.rst
towerlib/USAGE.rst
towerlib/__init__.py
towerlib/_version.py
towerlib/dev-requirements.txt
towerlib/requirements.txt
towerlib/towerlib.py
towerlib/towerlibexceptions.py
towerlib/__pycache__/__init__.cpython-37.pyc
towerlib/__pycache__/__init__.cpython-39.pyc
towerlib/__pycache__/_version.cpython-37.pyc
towerlib/__pycache__/_version.cpython-39.pyc
towerlib/__pycache__/towerlib.cpython-37.pyc
towerlib/__pycache__/towerlib.cpython-39.pyc
towerlib/__pycache__/towerlibexceptions.cpython-37.pyc
towerlib/__pycache__/towerlibexceptions.cpython-39.pyc
towerlib/entities/__init__.py
towerlib/entities/core.py
towerlib/entities/credential.py
towerlib/entities/group.py
towerlib/entities/host.py
towerlib/entities/instance.py
towerlib/entities/inventory.py
towerlib/entities/inventory_script.py
towerlib/entities/inventory_source.py
towerlib/entities/job.py
towerlib/entities/notification.py
towerlib/entities/organization.py
towerlib/entities/project.py
towerlib/entities/role.py
towerlib/entities/schedule.py
towerlib/entities/settings.py
towerlib/entities/team.py
towerlib/entities/user.py
towerlib/entities/__pycache__/__init__.cpython-37.pyc
towerlib/entities/__pycache__/__init__.cpython-39.pyc
towerlib/entities/__pycache__/core.cpython-37.pyc
towerlib/entities/__pycache__/core.cpython-39.pyc
towerlib/entities/__pycache__/credential.cpython-37.pyc
towerlib/entities/__pycache__/credential.cpython-39.pyc
towerlib-3.16.0.dist-info/AUTHORS.rst
towerlib-3.16.0.dist-info/LICENSE
towerlib-3.16.0.dist-info/METADATA
towerlib-3.16.0.dist-info/WHEEL
towerlib-3.16.0.dist-info/top_level.txt
towerlib-3.16.0.dist-info/RECORD
