Metadata-Version: 2.1
Name: towerlib
Version: 3.16.0
Summary: A python library to interface with ansible tower's (awx) api.
Home-page: https://github.com/schubergphilis/towerlib.git
Author: Costas Tyfoxylos
Author-email: ctyfoxylos@schubergphilis.com
License: MIT
Keywords: towerlib tower awx api ansible python
Classifier: Development Status :: 4 - Beta
Classifier: Intended Audience :: Developers
Classifier: License :: OSI Approved :: MIT License
Classifier: Natural Language :: English
Classifier: Programming Language :: Python :: 3.7
License-File: LICENSE
License-File: AUTHORS.rst
Requires-Dist: dateutils ~=0.6.12
Requires-Dist: beautifulsoup4 ~=4.13.4 ; python_full_version >= "3.7.0"
Requires-Dist: cachetools ~=5.5.2 ; python_version >= "3.7"
Requires-Dist: requests ~=2.32.4 ; python_version >= "3.8"
